openbtmixing/__init__.py
openbtmixing/ambrt.lo
openbtmixing/ambrt.o
openbtmixing/amxbrt.lo
openbtmixing/amxbrt.o
openbtmixing/brt.lo
openbtmixing/brt.o
openbtmixing/brtfuns.lo
openbtmixing/brtfuns.o
openbtmixing/brtmoves.lo
openbtmixing/brtmoves.o
openbtmixing/cli.o
openbtmixing/crn.lo
openbtmixing/crn.o
openbtmixing/interface_helpers.py
openbtmixing/libambrt.la
openbtmixing/libamxbrt.la
openbtmixing/libbrt.la
openbtmixing/libcrn.la
openbtmixing/libmbrt.la
openbtmixing/libmxbrt.la
openbtmixing/libpsbrt.la
openbtmixing/libsbrt.la
openbtmixing/libsinglebinomial.la
openbtmixing/libsinglepoisson.la
openbtmixing/libtree.la
openbtmixing/mbrt.lo
openbtmixing/mbrt.o
openbtmixing/mixandemulate.o
openbtmixing/mixandemulatepred.o
openbtmixing/mixingwts.o
openbtmixing/mopareto.o
openbtmixing/mxbrt.lo
openbtmixing/mxbrt.o
openbtmixing/openbtcli
openbtmixing/openbtmixing
openbtmixing/openbtmixing.py
openbtmixing/openbtmixingpred
openbtmixing/openbtmixingwts
openbtmixing/openbtmopareto
openbtmixing/openbtpred
openbtmixing/openbtsobol
openbtmixing/openbtvartivity
openbtmixing/pred.o
openbtmixing/psbrt.lo
openbtmixing/psbrt.o
openbtmixing/sbrt.lo
openbtmixing/sbrt.o
openbtmixing/singlebinomial.lo
openbtmixing/singlebinomial.o
openbtmixing/singlepoisson.lo
openbtmixing/singlepoisson.o
openbtmixing/sobol.o
openbtmixing/tnorm.lo
openbtmixing/tnorm.o
openbtmixing/tree.lo
openbtmixing/tree.o
openbtmixing/treefuns.lo
openbtmixing/treefuns.o
openbtmixing/vartivity.o
openbtmixing/.libs/ambrt.o
openbtmixing/.libs/amxbrt.o
openbtmixing/.libs/brt.o
openbtmixing/.libs/brtfuns.o
openbtmixing/.libs/brtmoves.o
openbtmixing/.libs/crn.o
openbtmixing/.libs/libambrt.0.dylib
openbtmixing/.libs/libambrt.a
openbtmixing/.libs/libambrt.dylib
openbtmixing/.libs/libambrt.la
openbtmixing/.libs/libambrt.lai
openbtmixing/.libs/libamxbrt.0.dylib
openbtmixing/.libs/libamxbrt.a
openbtmixing/.libs/libamxbrt.dylib
openbtmixing/.libs/libamxbrt.la
openbtmixing/.libs/libamxbrt.lai
openbtmixing/.libs/libbrt.0.dylib
openbtmixing-1.0.1.dist-info/LICENSE
openbtmixing-1.0.1.dist-info/METADATA
openbtmixing-1.0.1.dist-info/WHEEL
openbtmixing-1.0.1.dist-info/top_level.txt
openbtmixing-1.0.1.dist-info/RECORD
