Metadata-Version: 2.1
Name: openbtmixing
Version: 1.0.1
Summary: A python packge for model mixing using Bayesian Additive Regression Trees
Author-email: John Yannotty <yannotty.1@buckeyemail.osu.edu>
Classifier: Programming Language :: Python :: 3
Classifier: License :: OSI Approved :: MIT License
Classifier: Operating System :: OS Independent
Requires-Python: >=3.8
License-File: LICENSE
